nudgeops/__init__.py
nudgeops/core/__init__.py
nudgeops/core/detectors.py
nudgeops/core/interventions.py
nudgeops/core/scorer.py
nudgeops/core/state.py
nudgeops/embedding/__init__.py
nudgeops/embedding/service.py
nudgeops/embedding/utils.py
nudgeops/integrations/__init__.py
nudgeops/integrations/apply_guard.py
nudgeops/integrations/extractors.py
nudgeops/integrations/langgraph.py
nudgeops/integrations/universal_guard.py
nudgeops/observability/__init__.py
nudgeops/observability/langfuse.py
nudgeops/observability/logging.py
nudgeops/smart/__init__.py
nudgeops/smart/events.py
nudgeops/smart/failure_memory.py
nudgeops/smart/guard.py
nudgeops/smart/hashers.py
nudgeops/smart/langgraph_integration.py
nudgeops/smart/observability.py
nudgeops/smart/thought_normalizer.py
nudgeops/testing/__init__.py
nudgeops/testing/interfaces.py
nudgeops/testing/loop_inducing_tools.py
nudgeops/testing/openai_agent.py
nudgeops/testing/step_adapter.py
nudgeops/testing/environments/__init__.py
nudgeops/testing/environments/code_env.py
nudgeops/testing/environments/shopping_env.py
nudgeops/testing/scenarios/__init__.py
nudgeops/testing/scenarios/code_scenarios.py
nudgeops/testing/scenarios/shopping_scenarios.py
nudgeops-0.2.6.dist-info/METADATA
nudgeops-0.2.6.dist-info/WHEEL
nudgeops-0.2.6.dist-info/licenses/LICENSE
nudgeops-0.2.6.dist-info/RECORD
