Metadata-Version: 2.4
Name: nudgeops
Version: 0.2.6
Summary: Runtime semantic guardrails for AI agents. Detect loops. Nudge agents back on track.
Project-URL: Homepage, https://github.com/luv91/nudgeops
Project-URL: Documentation, https://github.com/luv91/nudgeops#readme
Project-URL: Repository, https://github.com/luv91/nudgeops
Project-URL: Issues, https://github.com/luv91/nudgeops/issues
Author: luv91
License: MIT
License-File: LICENSE
Keywords: agents,ai,guardrails,langgraph,llm,loop-detection
Classifier: Development Status :: 4 - Beta
Classifier: Intended Audience :: Developers
Classifier: License :: OSI Approved :: MIT License
Classifier: Programming Language :: Python :: 3
Classifier: Programming Language :: Python :: 3.10
Classifier: Programming Language :: Python :: 3.11
Classifier: Programming Language :: Python :: 3.12
Classifier: Topic :: Scientific/Engineering :: Artificial Intelligence
Classifier: Topic :: Software Development :: Libraries
Requires-Python: >=3.10
Requires-Dist: numpy>=1.24.0
Provides-Extra: all
Requires-Dist: langchain-core>=0.2.0; extra == 'all'
Requires-Dist: langfuse>=2.0.0; extra == 'all'
Requires-Dist: langgraph>=0.2.0; extra == 'all'
Requires-Dist: openai>=1.0.0; extra == 'all'
Requires-Dist: pytest-asyncio>=0.21.0; extra == 'all'
Requires-Dist: pytest>=7.0.0; extra == 'all'
Requires-Dist: python-dotenv>=1.0.0; extra == 'all'
Provides-Extra: dev
Requires-Dist: pytest-asyncio>=0.21.0; extra == 'dev'
Requires-Dist: pytest>=7.0.0; extra == 'dev'
Requires-Dist: python-dotenv>=1.0.0; extra == 'dev'
Provides-Extra: langfuse
Requires-Dist: langfuse>=2.0.0; extra == 'langfuse'
Provides-Extra: langgraph
Requires-Dist: langchain-core>=0.2.0; extra == 'langgraph'
Requires-Dist: langgraph>=0.2.0; extra == 'langgraph'
Provides-Extra: openai
Requires-Dist: openai>=1.0.0; extra == 'openai'
